lunchsimple/__init__.py
lunchsimple/__main__.py
lunchsimple/app.py
lunchsimple/cli.py
lunchsimple-0.3.1.dist-info/METADATA
lunchsimple-0.3.1.dist-info/WHEEL
lunchsimple-0.3.1.dist-info/entry_points.txt
lunchsimple-0.3.1.dist-info/licenses/LICENSE
lunchsimple-0.3.1.dist-info/RECORD
