Metadata-Version: 2.3
Name: lunchsimple
Version: 0.3.1
Summary: Sync Wealthsimple with Lunch Money.
Project-URL: Homepage, https://sr.ht/~colbyhub/lunchsimple/
Project-URL: Issues, https://todo.sr.ht/~colbyhub/lunchsimple
Author-email: Colby Hubscher <colby@colbyhub.com>
License-Expression: MIT
License-File: LICENSE
Classifier: Operating System :: OS Independent
Classifier: Programming Language :: Python :: 3
Requires-Python: >=3.12
Requires-Dist: keyring>=25.6.0
Requires-Dist: lunchable>=1.4.2
Requires-Dist: pre-commit>=4.0.1
Requires-Dist: ruff>=0.8.6
Requires-Dist: twine>=6.0.1
Requires-Dist: typer>=0.15.1
Requires-Dist: ws-api>=0.10.0
